LICENSE
README.md
rigby/__init__.py
rigby/cli.py
rigby/core.py
rigby/display.py
rigby-0.1.3.dist-info/METADATA
rigby-0.1.3.dist-info/WHEEL
rigby-0.1.3.dist-info/entry_points.txt
rigby-0.1.3.dist-info/licenses/LICENSE
rigby-0.1.3.dist-info/RECORD
