Metadata-Version: 2.4
Name: rigby
Version: 0.1.3
Summary: A tool to remove empty lines and clean up rigby in Python files
Project-URL: Homepage, https://github.com/lothartj/rigby
Project-URL: Issues, https://github.com/lothartj/rigby/issues
Author-email: Lothar Tjipueja <lotharwebdev@gmail.com>
License-File: LICENSE
Classifier: License :: OSI Approved :: MIT License
Classifier: Operating System :: OS Independent
Classifier: Programming Language :: Python :: 3
Requires-Python: >=3.8
Requires-Dist: click>=8.0.0
Requires-Dist: loguru>=0.7.0
Requires-Dist: pydantic>=2.0.0
Requires-Dist: rich>=13.0.0
Requires-Dist: typing-extensions>=4.0.0
